uio_api/INTERNAL.md
uio_api/README.md
uio_api/__about__.py
uio_api/__init__.py
uio_api/constants.py
uio_api/logging.py
uio_api/test.py
uio_api/test_ldap.py
uio_api/config/__init__.py
uio_api/config/base.py
uio_api/config/factory.py
uio_api/config/module.py
uio_api/config/paths.py
uio_api/config/registry.py
uio_api/config/settings.py
uio_api/core/__init__.py
uio_api/core/client.py
uio_api/core/endpoints.py
uio_api/core/enums.py
uio_api/core/factory_utils.py
uio_api/core/auth/__init__.py
uio_api/core/auth/httpx_auth.py
uio_api/core/auth/provider.py
uio_api/core/retry/__init__.py
uio_api/core/retry/policy.py
uio_api/core/tokens/__init__.py
uio_api/core/tokens/loader_abstract.py
uio_api/core/tokens/loader_keyring.py
uio_api/core/tokens/loader_toml.py
uio_api/core/tokens/scope.py
uio_api/modules/README.md
uio_api/modules/__init__.py
uio_api/modules/example/__init__.py
uio_api/modules/example/factory.py
uio_api/modules/example/profile.py
uio_api/modules/ldap/README.md
uio_api/modules/ldap/__init__.py
uio_api/modules/ldap/client.py
uio_api/modules/ldap/endpoints.py
uio_api/modules/ldap/factory.py
uio_api/modules/mreg/__init__.py
uio_api/modules/mreg/client.py
uio_api/modules/mreg/endpoints.py
uio_api/modules/mreg/factory.py
uio_api/modules/mreg/helpers.py
uio_api/modules/mreg/limits.py
uio_api/modules/mreg/profile.py
uio_api/modules/nivlheim/README.md
uio_api/modules/nivlheim/__init__.py
uio_api/modules/nivlheim/client.py
uio_api/modules/nivlheim/endpoints.py
uio_api/modules/nivlheim/factory.py
uio_api/profiles/__init__.py
uio_api/profiles/base.py
uio_api-0.1.1.dist-info/METADATA
uio_api-0.1.1.dist-info/WHEEL
uio_api-0.1.1.dist-info/RECORD
