Metadata-Version: 2.4
Name: uio_api
Version: 0.1.1
Summary: UIO generic API wrappers with pluggable auth, retries, and pagination profiles
Project-URL: Source, https://github.uio.no/IT-DIA/MREG-API-TEST
Author-email: Øistein Søvik <Oistein.Sovik.92@gmail.com>
License-Expression: MIT
Requires-Python: >=3.12
Requires-Dist: httpx>=0.28.1
Requires-Dist: keyring>=25.2.1
Requires-Dist: ldap3>=2.9.1
Requires-Dist: loguru>=0.7.3
Requires-Dist: platformdirs>=4.2.2
Requires-Dist: tomlkit>=0.13.2
Provides-Extra: build
Requires-Dist: build>=1.3.0; extra == 'build'
Requires-Dist: hatch-vcs>=0.5.0; extra == 'build'
Requires-Dist: hatchling>=1.27.0; extra == 'build'
Requires-Dist: twine>=6.2.0; extra == 'build'
Provides-Extra: dev
Requires-Dist: mypy>=1.17.1; extra == 'dev'
Requires-Dist: pytest-cov>=6.2.1; extra == 'dev'
Requires-Dist: pytest>=8.4.2; extra == 'dev'
Requires-Dist: ruff>=0.12.11; extra == 'dev'
